Workbook

Sheet Top-Sheet
B2: Thapovan Info Systems Private Limited
B3: Salary Sheet - April 2024
B6: Sl. No. | C6: Particulars | D6: Name of the Sheet
B7: 1 | C7: =P.1!B5 -> Salary Sheet - April 2024 | D7: =P.1!B6 -> P.1
B8: =B7+1 -> 2 | C8: =P.2!B4 -> Bank Upload | D8: =P.2!B5 -> P.2
B9: =B8+1 -> 3 | C9: =P.3!B4 -> TDS Computation | D9: =P.3!B5 -> P.3
B10: =B9+1 -> 4 | C10: =P.4!B4 -> Gratuity Computation | D10: =P.4!B5 -> P.4
B11: =B10+1 -> 5 | C11: =P.5!B4 -> Loan master | D11: =P.5!B5 -> P.5

Sheet P.1
F1: Band | G1: Range CTC | J1: Fixed | K1: Variable
F2: I | G2: 0 | H2: to | I2: 600000 | J2: 0.9 | K2: =100%-J2 -> 0.1
F3: II | G3: =+I2+1 -> 600001 | H3: to | I3: 1000000 | J3: 0.65 | K3: =100%-J3 -> 0.35
B4: ='Top-Sheet'!B2 -> Thapovan Info Systems Private Limited | F4: III | G4: =+I3+1 -> 1000001 | H4: to | I4: 1500000 | J4: 0.6 | K4: =100%-J4 -> 0.4
B5: ='Top-Sheet'!B3 -> Salary Sheet - April 2024 | F5: IV | G5: =+I4+1 -> 1500001 | H5: to | I5: 3500000 | J5: 0.55 | K5: =100%-J5 -> 0.45
B6: P.1 | F6: V | G6: =+I5+1 -> 3500001 | H6: and | I6: above | J6: 0.5 | K6: =100%-J6 -> 0.5
E8: 45291
B9: Sl. No. | C9: Employee Number | D9: Employee Name | E9: Joining Date | F9: Date of Releiving | G9: No of Days | H9: LOP | I9: Band | J9: 2024 CTC Yearly | K9: CTC Yearly | L9: CTC Monthly | M9: Gratuity Changed | N9: Fixed | O9: Variable Pay | P9: Fixed | Q9: Variable | R9: Basic | S9: HRA | T9: Special Allowance | U9: IPI | V9: TPI | W9: CPI | X9: Loyalty bonus | Y9: Star Club | Z9: Project Incentive | AA9: Reimbursement | AB9: Leave Encashment | AC9: Annual Bonus | AD9: Total Earnings | AE9: EPF Basics | AF9: Gratuity | AG9: Total other than Spl Allowance | AH9: EPF | AI9: ESI | AJ9: PT | AK9: Salary Loan | AL9: TDS | AM9: Other Deduction | AN9: LOP Deduction | AO9: Net Payable | AQ9: Leave Encashment | AS9: Old Net Payable | AT9: Appraisal Salary
B10: 1 | C10: 34 | D10: Prabu A | E10: 38019 | G10: 30 | H10: 0 | I10: IV | J10: 1916383.3 | K10: =J10 -> 1916383.3 | L10: =K10/12 -> 159698.61 | N10: =VLOOKUP(C10,'[1]Final Apprisal'!$B$2:$U$82,20,) -> 0.51457976 | O10: =1-N10 -> 0.48542024 | P10: =L10*N10 -> 82177.673 | Q10: =L10*O10 -> 77520.939 | R10: =P10*0.5 -> 41088.837 | S10: =R10*0.5 -> 20544.418 | T10: =L10-SUM(AF10:AH10) -> 16768.994 | U10: =Q10*0.5 -> 38760.469 | V10: =Q10*0.25 -> 19380.235 | W10: =Q10*0.25 -> 19380.235 | X10: 0 | Y10: 0 | Z10: 0 | AA10: 0 | AB10: =AR10 -> 14381.093 | AC10: 0 | AD10: =SUM(R10:Z10) -> 155923.19 | AE10: 15000 | AF10: =P.4!K8 -> 1975.4248 | AG10: =SUM(R10,S10,U10,V10,W10) -> 139154.19 | AH10: =AE10*12% -> 1800 | AI10: 0 | AJ10: =2500/12 -> 208.33333 | AK10: =P.5!J8 -> 0 | AL10: =P.3!O8 -> 21800 | AM10: 0 | AN10: =L10*H10/G10 -> 0 | AO10: =ROUNDUP(SUM(AA10:AD10)-SUM(AH10:AN10),0) -> 146496 | AP10: =AD10-AN10 -> 155923.19 | AQ10: 7 | AR10: =AQ10/30*(R10+S10) -> 14381.093 | AS10: 140257 | AT10: =AO10-AS10 -> 6239
B11: =B10+1 -> 2 | C11: 38 | D11: Jeyanthi J | E11: 39426 | G11: 30 | H11: 0 | I11: IV | J11: 1605000 | K11: =J11 -> 1605000 | L11: =K11/12 -> 133750 | N11: =VLOOKUP(C11,'[1]Final Apprisal'!$B$2:$U$82,20,) -> 0.3833 | O11: =1-N11 -> 0.6167 | P11: =L11*N11 -> 51266.375 | Q11: =L11*O11 -> 82483.625 | R11: =P11*0.5 -> 25633.188 | S11: =R11*0.5 -> 12816.594 | T11: =L11-SUM(AF11:AH11) -> 9784.229 | U11: =Q11*0.5 -> 41241.812 | V11: =Q11*0.25 -> 20620.906 | W11: =Q11*0.25 -> 20620.906 | X11: 0 | Y11: 0 | Z11: 0 | AA11: 0 | AB11: =AR11 -> 8971.6156 | AC11: 0 | AD11: =SUM(R11:Z11) -> 130717.64 | AE11: 15000 | AF11: =P.4!K9 -> 1232.3648 | AG11: =SUM(R11,S11,U11,V11,W11) -> 120933.41 | AH11: =AE11*12% -> 1800 | AI11: 0 | AJ11: =2500/12 -> 208.33333 | AK11: =P.5!J9 -> 0 | AL11: =P.3!O9 -> 13800 | AM11: 0 | AN11: =L11*H11/G11 -> 0 | AO11: =ROUNDUP(SUM(AA11:AD11)-SUM(AH11:AN11),0) -> 123881 | AP11: =AD11-AN11 -> 130717.64 | AQ11: 7 | AR11: =AQ11/30*(R11+S11) -> 8971.6156 | AS11: 123881 | AT11: =AO11-AS11 -> 0

Sheet P.2
B2: =P.1!B4 -> Thapovan Info Systems Private Limited
B3: =P.1!B5 -> Salary Sheet - April 2024
B4: Bank Upload
B5: P.2
B7: Sl. No. | C7: Narration | D7: Employee Number | E7: Employee Name | F7: Bank Account Number | G7: IFS Code | H7: Account Type | I7: Amount (in Rs.) | J7: Date | K7: Comma | L7: Bank Upload Line
B8: 1 | C8: Salary April 2024 | D8: =P.1!C10 -> 34 | E8: =P.1!D10 -> Prabu A | F8: 50100172023950 | G8: HDFC0000206 | H8: 11 | I8: =P.1!AT10 -> 6239 | J8: =TEXT(TODAY(),"yyyymmdd") -> 20250717 | K8: , | L8: =C8&K8&E8&K8&F8&K8&G8&K8&H8&K8&I8&K8&J8 -> Salary April 2024,Prabu A,50100172023950,HDFC0000206,11,6239,20250717
B9: =B8+1 -> 2 | C9: Salary April 2024 | D9: =P.1!C11 -> 38 | E9: =P.1!D11 -> Jeyanthi J | F9: 50100504907150 | G9: HDFC0000260 | H9: 11 | I9: =P.1!AT11 -> 0 | J9: =TEXT(TODAY(),"yyyymmdd") -> 20250717 | K9: , | L9: =C9&K9&E9&K9&F9&K9&G9&K9&H9&K9&I9&K9&J9 -> Salary April 2024,Jeyanthi J,50100504907150,HDFC0000260,11,0,20250717

Sheet P.3
B2: =P.1!B4 -> Thapovan Info Systems Private Limited
B3: =P.1!B5 -> Salary Sheet - April 2024
B4: TDS Computation
B5: P.3
B7: Sl. No. | C7: Employee Number | D7: Employee Name | E7: Total Earnings | F7: Other Earnings (Salary) | G7: Standard Deduction | H7: Taxable Income | I7: Tax on Total Income | J7: Rebate | K7: Tax Payable | L7: Cess | M7: Total Tax Payable | N7: TDS per month | O7: 45383 | P7: 45413 | Q7: 45444 | R7: 45474 | S7: 45505 | T7: 45536 | U7: 45566 | V7: 45597 | W7: 45627 | X7: 45658 | Y7: 45689 | Z7: 45717 | AA7: Total TDS Deducted | AB7: Balance to be Deducted
B8: 1 | C8: =P.1!C10 -> 34 | D8: =P.1!D10 -> Prabu A | E8: =P.1!AD10*12 -> 1871078.2 | F8: =P.1!AR10 -> 14381.093 | G8: 50000 | H8: =SUM(E8:F8)-G8 -> 1835459.3 | I8: =IF(H8>1500000,((H8-1500000)*30%+150000),(IF(H8>1200000,((H8-1200000)*20%+90000),IF(H8>900000,((H8-900000)*15%+45000),IF(H8>600000,((H8-600000)*10%+15000),IF(H8>300000,(H8-300000)*5%,0)))))) -> 250637.8 | J8: =IF(H8>700000,0,I8) -> 0 | K8: =I8-J8 -> 250637.8 | L8: =K8*4% -> 10025.512 | M8: =SUM(K8:L8) -> 260663.31 | N8: =CEILING(M8/12,100) -> 21800 | O8: =N8 -> 21800 | AA8: =SUM(O8:Z8) -> 21800 | AB8: =N8*12-AA8 -> 239800
B9: =B8+1 -> 2 | C9: =P.1!C11 -> 38 | D9: =P.1!D11 -> Jeyanthi J | E9: =P.1!AD11*12 -> 1568611.6 | F9: =P.1!AR11 -> 8971.6156 | G9: 50000 | H9: =SUM(E9:F9)-G9 -> 1527583.2 | I9: =IF(H9>1500000,((H9-1500000)*30%+150000),(IF(H9>1200000,((H9-1200000)*20%+90000),IF(H9>900000,((H9-900000)*15%+45000),IF(H9>600000,((H9-600000)*10%+15000),IF(H9>300000,(H9-300000)*5%,0)))))) -> 158274.97 | J9: =IF(H9>700000,0,I9) -> 0 | K9: =I9-J9 -> 158274.97 | L9: =K9*4% -> 6330.9989 | M9: =SUM(K9:L9) -> 164605.97 | N9: =CEILING(M9/12,100) -> 13800 | O9: =N9 -> 13800 | AA9: =SUM(O9:Z9) -> 13800 | AB9: =N9*12-AA9 -> 151800

Sheet P.4
B2: =P.1!B4 -> Thapovan Info Systems Private Limited | F2: 45383
B3: =P.1!B5 -> Salary Sheet - April 2024
B4: Gratuity Computation
B5: P.4
B7: Sl. No. | C7: Employee Number | D7: Employee Name | E7: Joining Date | F7: Number of years of service | G7: Current Basic Salary | H7: Old Basic Salary | I7: Gratuity per month - Current | J7: Gratuity per month - Old | K7: Total Gratuity per month
B8: 1 | C8: =P.1!C10 -> 34 | D8: =P.1!D10 -> Prabu A | E8: =P.1!E10 -> 38019 | F8: =ROUND(($F$2-E8)/365.25,0) -> 20 | G8: =P.1!R10 -> 41088.837 | H8: 41088.837 | I8: =G8*15/26/12 -> 1975.4248 | J8: =(G8-H8)*F8*15/26/12 -> 0 | K8: =SUM(I8:J8) -> 1975.4248
B9: =B8+1 -> 2 | C9: =P.1!C11 -> 38 | D9: =P.1!D11 -> Jeyanthi J | E9: =P.1!E11 -> 39426 | F9: =ROUND(($F$2-E9)/365.25,0) -> 16 | G9: =P.1!R11 -> 25633.188 | H9: 25633.188 | I9: =G9*15/26/12 -> 1232.3648 | J9: =(G9-H9)*F9*15/26/12 -> 0 | K9: =SUM(I9:J9) -> 1232.3648

Sheet P.5
B2: =P.1!B4 -> Thapovan Info Systems Private Limited
B3: =P.1!B5 -> Salary Sheet - April 2024
B4: Loan master
B5: P.5
B7: Sl. No. | C7: Employee Number | D7: Employee Name | E7: Amount of Loan Taken | F7: Date of Loan Issued | G7: Tenure of the Loan (in months) | H7: Monthly Instalments | I7: Opening balance as on 01/04/2024 | J7: 45383 | K7: 45413 | L7: 45444 | M7: 45474 | N7: 45505 | O7: 45536 | P7: 45566 | Q7: 45597 | R7: 45627 | S7: 45658 | T7: 45689 | U7: 45717 | V7: Closing Balance as on 31/03/2025
B8: 1 | C8: =P.1!C10 -> 34 | D8: =P.1!D10 -> Prabu A
B9: =B8+1 -> 2 | C9: =P.1!C11 -> 38 | D9: =P.1!D11 -> Jeyanthi J
